wraplorenzmie/__init__.py
wraplorenzmie/fits/__init__.py
wraplorenzmie/fits/fit.py
wraplorenzmie/pylorenzmie/__init__.py
wraplorenzmie/pylorenzmie/analysis/Feature.py
wraplorenzmie/pylorenzmie/analysis/Frame.py
wraplorenzmie/pylorenzmie/analysis/Mask.py
wraplorenzmie/pylorenzmie/analysis/Trajectory.py
wraplorenzmie/pylorenzmie/analysis/Video.py
wraplorenzmie/pylorenzmie/analysis/__init__.py
wraplorenzmie/pylorenzmie/fitting/Estimator.py
wraplorenzmie/pylorenzmie/fitting/Localizer.py
wraplorenzmie/pylorenzmie/fitting/Optimizer.py
wraplorenzmie/pylorenzmie/fitting/__init__.py
wraplorenzmie/pylorenzmie/fitting/catchEstimator.py
wraplorenzmie/pylorenzmie/fitting/catchLocalizer.py
wraplorenzmie/pylorenzmie/fitting/circletransform.py
wraplorenzmie/pylorenzmie/fitting/localize.py
wraplorenzmie/pylorenzmie/lmtool/DoubleSlider.py
wraplorenzmie/pylorenzmie/lmtool/DoubleSpinBox.py
wraplorenzmie/pylorenzmie/lmtool/LMTool.py
wraplorenzmie/pylorenzmie/lmtool/__init__.py
wraplorenzmie/pylorenzmie/tests/__init__.py
wraplorenzmie/pylorenzmie/tests/test_cupylorenzmie.py
wraplorenzmie/pylorenzmie/tests/test_feature.py
wraplorenzmie/pylorenzmie/tests/test_frame.py
wraplorenzmie/pylorenzmie/tests/test_instrument.py
wraplorenzmie/pylorenzmie/tests/test_lmhologram.py
wraplorenzmie/pylorenzmie/tests/test_lorenzmie.py
wraplorenzmie/pylorenzmie/tests/test_mask.py
wraplorenzmie/pylorenzmie/tests/test_optimizer.py
wraplorenzmie/pylorenzmie/tests/test_particle.py
wraplorenzmie/pylorenzmie/tests/test_sphere.py
wraplorenzmie/pylorenzmie/tests/test_utilities.py
wraplorenzmie/pylorenzmie/theory/Aberrations.py
wraplorenzmie/pylorenzmie/theory/Instrument.py
wraplorenzmie/pylorenzmie/theory/LMHologram.py
wraplorenzmie/pylorenzmie/theory/LorenzMie.py
wraplorenzmie/pylorenzmie/theory/Particle.py
wraplorenzmie/pylorenzmie/theory/Sphere.py
wraplorenzmie/pylorenzmie/theory/__init__.py
wraplorenzmie/pylorenzmie/theory/cupyLorenzMie.py
wraplorenzmie/pylorenzmie/utilities/__init__.py
wraplorenzmie-1.0.0.dist-info/LICENSE
wraplorenzmie-1.0.0.dist-info/METADATA
wraplorenzmie-1.0.0.dist-info/WHEEL
wraplorenzmie-1.0.0.dist-info/top_level.txt
wraplorenzmie-1.0.0.dist-info/RECORD
